<?xml version="1.0" encoding="utf-8"?>
<SdkMessageProcessingStep Name="Inject OAuth password grant for import solution" SdkMessageProcessingStepId="{a03ed163-c78a-e911-a97b-002248010929}" xmlns:xsi="http://www.w3.org/2001/XMLSchema-instance">
  <PluginTypeName>Capgemini.DevelopmentHub.Develop.Plugins.InjectSecureConfig, Capgemini.DevelopmentHub.Develop, Version=1.0.0.0, Culture=neutral, PublicKeyToken=ea2317363a0474b4</PluginTypeName>
  <PluginTypeId>9f3ed163-c78a-e911-a97b-002248010929</PluginTypeId>
  <PrimaryEntity>cap_environment</PrimaryEntity>
  <AsyncAutoDelete>0</AsyncAutoDelete>
  <FilteringAttributes></FilteringAttributes>
  <InvocationSource>0</InvocationSource>
  <Mode>0</Mode>
  <Rank>0</Rank>
  <SdkMessageId>{b0aad088-c18a-e911-a97e-0022480186c3}</SdkMessageId>
  <EventHandlerTypeCode>4602</EventHandlerTypeCode>
  <Stage>20</Stage>
  <IsCustomizable>1</IsCustomizable>
  <IsHidden>0</IsHidden>
  <SupportedDeployment>0</SupportedDeployment>
  <IntroducedVersion>1.0</IntroducedVersion>
  <SdkMessageProcessingStepImages />
</SdkMessageProcessingStep>